LICENSE.txt
MANIFEST.in
README.md
setup.cfg
setup.py
bear_hug/__init__.py
bear_hug/atlas_viewer.py
bear_hug/bear_hug.py
bear_hug/bear_utilities.py
bear_hug/ecs.py
bear_hug/ecs_widgets.py
bear_hug/event.py
bear_hug/resources.py
bear_hug/sound.py
bear_hug/widgets.py
bear_hug.egg-info/PKG-INFO
bear_hug.egg-info/SOURCES.txt
bear_hug.egg-info/dependency_links.txt
bear_hug.egg-info/requires.txt
bear_hug.egg-info/top_level.txt
bear_hug/demo_assets/cp437_12x12.png
bear_hug/demo_assets/tank.txt
bear_hug/demo_assets/test_atlas.json
bear_hug/demo_assets/test_atlas.xp
bear_hug/demo_assets/tree_lamp.xp