Metadata-Version: 1.2
Name: bear-hug
Version: 0.1.1
Summary: An object-oriented ECS library for ASCII games. Wraps bearlibterminal.
Home-page: https://github.com/SynedraAcus/bear_hug
Author: Alexey Morozov
Author-email: alexeymorozov1991@gmail.com
License: MIT
Download-URL: https://github.com/SynedraAcus/bear_hug/archive/0.1.1.tar.gz
Keywords: gamedev,ascii,ASCII
Platform: UNKNOWN
Requires-Python: >=3.6
